ChangeLog
LICENSE.txt
README.md
pyproject.toml
ecspylibs/__init__.py
ecspylibs/configfile.py
ecspylibs/crypt.py
ecspylibs/logging.py
ecspylibs/parallel.py
ecspylibs/password.py
ecspylibs/sendemail.py
ecspylibs-2.0.2.dist-info/LICENSE.txt
ecspylibs-2.0.2.dist-info/METADATA
ecspylibs-2.0.2.dist-info/WHEEL
ecspylibs-2.0.2.dist-info/entry_points.txt
ecspylibs-2.0.2.dist-info/RECORD
