Metadata-Version: 2.1
Name: ecspylibs
Version: 2.0.2
Summary: Local python libraries used across multiple programs
License: GPL-3.0-or-later
Keywords: configfile
Author: Thomas R. Stevenson
Author-email: aa0026@wayne.edu
Maintainer: Thomas R. Stevenson
Maintainer-email: aa0026@wayne.edu
Requires-Python: >=3.11,<4.0
Classifier: Development Status :: 3 - Alpha
Classifier: Environment :: Console
Classifier: License :: OSI Approved :: GNU General Public License v3 or later (GPLv3+)
Classifier: License :: OSI Approved :: Python Software Foundation License
Classifier: Operating System :: OS Independent
Classifier: Programming Language :: Python :: 3
Classifier: Programming Language :: Python :: 3.11
Classifier: Programming Language :: Python :: 3.12
Classifier: Topic :: Software Development :: User Interfaces
Requires-Dist: autologging (>=1.3.2,<2.0.0)
Requires-Dist: lxml (>=4.9.4,<5.0.0)
Requires-Dist: pycryptodome (>=3.19.0,<4.0.0)
Requires-Dist: pyyaml (>=6.0.1,<7.0.0)
Requires-Dist: toml (>=0.10.2,<0.11.0)
Requires-Dist: xlrd (>=2.0.1,<3.0.0)
Requires-Dist: xmltodict (>=0.13.0,<0.14.0)
Project-URL: About Me, https://About.Me/Thomas.R.Stevenson
Project-URL: License, https://git.wayne.edu/ECS_Projects/ECScmdb/-/blob/master/LICENSE.txt
